sqlxw/__init__.py
sqlxw-0.0.1.dist-info/entry_points.txt
sqlxw-0.0.1.dist-info/LICENSE
sqlxw-0.0.1.dist-info/WHEEL
sqlxw-0.0.1.dist-info/METADATA
sqlxw-0.0.1.dist-info/RECORD
