Metadata-Version: 2.1
Name: sqlxw
Version: 0.0.1
Summary: Note Demo
Author-email: xinetzone <735613050@qq.com>
Maintainer-email: xinetzone <735613050@qq.com>
Requires-Python: >=3.10
Classifier: Development Status :: 4 - Beta
Classifier: Programming Language :: Python :: 3
Classifier: Framework :: Sphinx
Classifier: Framework :: Sphinx :: Theme
Classifier: License :: OSI Approved :: Apache Software License
Classifier: Operating System :: OS Independent
Requires-Dist: d2py
Requires-Dist: attrs
Requires-Dist: importlib-metadata>=4.12
Requires-Dist: pytest-cov ; extra == "coverage"
Requires-Dist: pytest-regressions ; extra == "coverage"
Requires-Dist: codecov ; extra == "coverage"
Requires-Dist: sqlxw[test] ; extra == "coverage"
Requires-Dist: pyyaml ; extra == "dev"
Requires-Dist: pre-commit ; extra == "dev"
Requires-Dist: note-demo[coverage] ; extra == "dev"
Requires-Dist: myst-nb ; extra == "doc"
Requires-Dist: xyzstyle ; extra == "doc"
Requires-Dist: sphinx-copybutton ; extra == "doc"
Requires-Dist: sphinxcontrib-bibtex ; extra == "doc"
Requires-Dist: sphinx-thebe ; extra == "doc"
Requires-Dist: sphinx-design ; extra == "doc"
Requires-Dist: sphinx-automodapi ; extra == "doc"
Requires-Dist: sphinx-sitemap ; extra == "doc"
Requires-Dist: sphinx-comments ; extra == "doc"
Requires-Dist: pytest ; extra == "test"
Requires-Dist: sqlxw[doc] ; extra == "test"
Project-URL: Home, https://github.com/xinetzone/sqlxw
Provides-Extra: coverage
Provides-Extra: dev
Provides-Extra: doc
Provides-Extra: test
